{
  "slug": "fc-stade-lausanne-ouchy",
  "seasons": {
    "2025": {
      "formation": "4-3-3",
      "players": [
        {
          "name": "Dany Da Silva",
          "position": "GK"
        },
        {
          "name": "Léo Besson",
          "position": "GK"
        },
        {
          "name": "Noah Noverraz",
          "position": "GK"
        },
        {
          "name": "Théo Barbet",
          "position": "CB"
        },
        {
          "name": "Breston Malula",
          "position": "CB"
        },
        {
          "name": "Rayan Kadima",
          "position": "CB"
        },
        {
          "name": "Nicola Sutter",
          "position": "CB"
        },
        {
          "name": "Lion de Oliveira",
          "position": "CB"
        },
        {
          "name": "Bastien Conus",
          "position": "CB"
        },
        {
          "name": "Issa Kaloga",
          "position": "CB"
        },
        {
          "name": "Patrick Sutter",
          "position": "CB"
        },
        {
          "name": "Hénoc Lukembila",
          "position": "CB"
        },
        {
          "name": "Johan Nkama",
          "position": "CM"
        },
        {
          "name": "Néhemie Lusuena",
          "position": "CM"
        },
        {
          "name": "Edmond Akichi",
          "position": "CM"
        },
        {
          "name": "Vasco Tritten",
          "position": "CM"
        },
        {
          "name": "Luca Gelato",
          "position": "CM"
        },
        {
          "name": "Ridge Mobulu",
          "position": "CM"
        },
        {
          "name": "Hugo Fargues",
          "position": "CM"
        },
        {
          "name": "Landry Nomel",
          "position": "ST"
        },
        {
          "name": "Mattéo Djoumgoué",
          "position": "ST"
        },
        {
          "name": "Keasse Bah",
          "position": "ST"
        },
        {
          "name": "Nathan Garcia",
          "position": "ST"
        },
        {
          "name": "Malko Sartoretti",
          "position": "ST"
        },
        {
          "name": "Loïc Socka Bongué",
          "position": "ST"
        },
        {
          "name": "François Mendy",
          "position": "ST"
        },
        {
          "name": "Latta N'Dabrou",
          "position": "ST"
        }
      ],
      "ratings": {
        "attack": 60,
        "midfield": 62,
        "defense": 66,
        "goalkeeping": 65
      },
      "source": "Transfermarkt — Brest (2025/2026)",
      "teamLabel": "Brest (2025-26)"
    }
  },
  "id": 5499,
  "name": "Brest",
  "badgeLocalPath": "/img/badges/brest.png",
  "group": "🌍 Otros"
}