{
  "slug": "wrexham",
  "seasons": {
    "2025": {
      "formation": "4-3-3",
      "players": [
        {
          "name": "Mark Howard",
          "position": "GK",
          "rating": 86
        },
        {
          "name": "Tom O'Connor",
          "position": "RB",
          "rating": 84
        },
        {
          "name": "Shaun Brisley",
          "position": "CB",
          "rating": 85
        },
        {
          "name": "Jordan Davies",
          "position": "CB",
          "rating": 85
        },
        {
          "name": "Elliot Lee",
          "position": "LB",
          "rating": 84
        },
        {
          "name": "Luke Young",
          "position": "CM",
          "rating": 84
        },
        {
          "name": "Ben Tozer",
          "position": "CM",
          "rating": 84
        },
        {
          "name": "Paul Mullin",
          "position": "RW",
          "rating": 85
        },
        {
          "name": "Ollie Palmer",
          "position": "ST",
          "rating": 86
        },
        {
          "name": "Jordan Tunnicliffe",
          "position": "LW",
          "rating": 85
        },
        {
          "name": "James Jones",
          "position": "CM",
          "rating": 84
        },
        {
          "name": "Christian Dibble",
          "position": "GK",
          "rating": 86
        },
        {
          "name": "Ollie Rathbone",
          "position": "RB",
          "rating": 84
        },
        {
          "name": "Ryan Barnett",
          "position": "CB",
          "rating": 85
        },
        {
          "name": "Anthony Forde",
          "position": "LB",
          "rating": 84
        },
        {
          "name": "Will Boyle",
          "position": "CM",
          "rating": 84
        },
        {
          "name": "Callum McFadzean",
          "position": "RW",
          "rating": 85
        },
        {
          "name": "Josh Bray",
          "position": "ST",
          "rating": 86
        },
        {
          "name": "Reece Hughes",
          "position": "LW",
          "rating": 85
        },
        {
          "name": "Manny Monthe",
          "position": "CB",
          "rating": 85
        },
        {
          "name": "Harry McClure",
          "position": "CM",
          "rating": 84
        }
      ],
      "ratings": {
        "attack": 66,
        "midfield": 66,
        "defense": 65,
        "goalkeeping": 65
      },
      "source": "Transfermarkt 🌍 Otros€” Wrexham AFC 2024-25 Championship",
      "teamLabel": "Wrexham AFC 2024-25 Championship"
    }
  },
  "id": 67,
  "name": "Wrexham AFC",
  "badgeLocalPath": "/img/badges/wrexham.png",
  "group": "🏴󠁧󠁢󠁥󠁮󠁧󠁿 Championship",
  "nameEn": "Wrexham AFC",
  "nameEs": "Wrexham AFC"
}